{
    "ratings": [
        {
            "attendance": "Mandatory", 
            "clarityColor": "good", 
            "easyColor": "average", 
            "helpColor": "good", 
            "helpCount": 0, 
            "id": 25302494, 
            "notHelpCount": 0, 
            "onlineClass": "", 
            "quality": "good", 
            "rClarity": 4, 
            "rClass": "HIST 376", 
            "rComments": "I like Schneider. Lectures can be long sometimes, but she is flexible to discussing whatever the class is interested in. I took three of her classes and felt she was an easy grader. Just read the appropriate material for her assignments and write like a college student and you will be fine. ", 
            "rDate": "10/27/2015", 
            "rEasy": 2, 
            "rEasyString": "2.0", 
            "rErrorMsg": null, 
            "rHelpful": 5, 
            "rInterest": "It's my life", 
            "rOverall": 4.5, 
            "rOverallString": "4.5", 
            "rStatus": 1, 
            "rTextBookUse": "Yes", 
            "rWouldTakeAgain": "N/A", 
            "sId": 1112, 
            "takenForCredit": "Yes", 
            "teacher": null, 
            "teacherGrade": "A", 
            "teacherRatingTags": [], 
            "unUsefulGrouping": "people", 
            "usefulGrouping": "people"
        }, 
        {
            "attendance": "N/A", 
            "clarityColor": "good", 
            "easyColor": "average", 
            "helpColor": "good", 
            "helpCount": 0, 
            "id": 24479860, 
            "notHelpCount": 0, 
            "onlineClass": "", 
            "quality": "good", 
            "rClarity": 4, 
            "rClass": "HIST200", 
            "rComments": "Schneider is a wonderful teacher! She is an excellent resource for improving writing techniques and made me even more passionate about history! She expects a lot out of her students which in fact builds a powerful educational atmosphere. You will learn a lot in her class and come away as a much stronger critical thinker!", 
            "rDate": "03/19/2015", 
            "rEasy": 3, 
            "rEasyString": "3.0", 
            "rErrorMsg": null, 
            "rHelpful": 4, 
            "rInterest": "It's my life", 
            "rOverall": 4, 
            "rOverallString": "4.0", 
            "rStatus": 1, 
            "rTextBookUse": "Yes", 
            "rWouldTakeAgain": "N/A", 
            "sId": 1112, 
            "takenForCredit": "Yes", 
            "teacher": null, 
            "teacherGrade": "N/A", 
            "teacherRatingTags": [], 
            "unUsefulGrouping": "people", 
            "usefulGrouping": "people"
        }, 
        {
            "attendance": "Mandatory", 
            "clarityColor": "poor", 
            "easyColor": "average", 
            "helpColor": "poor", 
            "helpCount": 0, 
            "id": 24123817, 
            "notHelpCount": 0, 
            "onlineClass": "", 
            "quality": "poor", 
            "rClarity": 1, 
            "rClass": "HIST271", 
            "rComments": "lectures were horrific, lasted the entire hour and twenty minutes.. and was almost verbatim what you read the night before. no actual discussion or elaboration on the the topics.. would often belittle students who answered questions with anything other than what she wanted to hear.. convinced me to change majors, so thankful for that i guess.. ", 
            "rDate": "12/17/2014", 
            "rEasy": 3, 
            "rEasyString": "3.0", 
            "rErrorMsg": null, 
            "rHelpful": 1, 
            "rInterest": "Sorta interested", 
            "rOverall": 1, 
            "rOverallString": "1.0", 
            "rStatus": 1, 
            "rTextBookUse": "Yes", 
            "rWouldTakeAgain": "N/A", 
            "sId": 1112, 
            "takenForCredit": "Yes", 
            "teacher": null, 
            "teacherGrade": "N/A", 
            "teacherRatingTags": [
                "Participation matters", 
                "LECTURE HEAVY", 
                "Skip class? You won't pass."
            ], 
            "unUsefulGrouping": "people", 
            "usefulGrouping": "people"
        }, 
        {
            "attendance": "N/A", 
            "clarityColor": "good", 
            "easyColor": "average", 
            "helpColor": "good", 
            "helpCount": 0, 
            "id": 23407009, 
            "notHelpCount": 0, 
            "onlineClass": "", 
            "quality": "good", 
            "rClarity": 5, 
            "rClass": "HIST200", 
            "rComments": "She had a great friendly approach and attitudes toward students. The readings are somehow demanding. Grades harsh at first and she was a good mentor to improve your writing skills. Towards the end, she give you a decent grade if you put more effort in the class.", 
            "rDate": "06/27/2014", 
            "rEasy": 2, 
            "rEasyString": "2.0", 
            "rErrorMsg": null, 
            "rHelpful": 5, 
            "rInterest": "Really into it", 
            "rOverall": 5, 
            "rOverallString": "5.0", 
            "rStatus": 1, 
            "rTextBookUse": "Yes", 
            "rWouldTakeAgain": "N/A", 
            "sId": 1112, 
            "takenForCredit": "N/A", 
            "teacher": null, 
            "teacherGrade": "N/A", 
            "teacherRatingTags": [], 
            "unUsefulGrouping": "people", 
            "usefulGrouping": "people"
        }, 
        {
            "attendance": "N/A", 
            "clarityColor": "good", 
            "easyColor": "poor", 
            "helpColor": "good", 
            "helpCount": 0, 
            "id": 22333909, 
            "notHelpCount": 0, 
            "onlineClass": "", 
            "quality": "good", 
            "rClarity": 5, 
            "rClass": "HIST271", 
            "rComments": "The way she teaches is very interesting and focus on multiple aspects of US History. The exams and paper are sort of challenge because required spending more time.I learned a lot from this class. The readings are intresting as well.", 
            "rDate": "11/17/2013", 
            "rEasy": 1, 
            "rEasyString": "1.0", 
            "rErrorMsg": null, 
            "rHelpful": 5, 
            "rInterest": "It's my life", 
            "rOverall": 5, 
            "rOverallString": "5.0", 
            "rStatus": 1, 
            "rTextBookUse": "Yes", 
            "rWouldTakeAgain": "N/A", 
            "sId": 1112, 
            "takenForCredit": "N/A", 
            "teacher": null, 
            "teacherGrade": "N/A", 
            "teacherRatingTags": [], 
            "unUsefulGrouping": "people", 
            "usefulGrouping": "people"
        }, 
        {
            "attendance": "Not Mandatory", 
            "clarityColor": "good", 
            "easyColor": "average", 
            "helpColor": "good", 
            "helpCount": 0, 
            "id": 22330475, 
            "notHelpCount": 1, 
            "onlineClass": "", 
            "quality": "good", 
            "rClarity": 5, 
            "rClass": "HIST272", 
            "rComments": "Her class is somehow demanding and necessary put much effort to have a decent grade, a lot readings, lectures are interesting, exams need lot memorization and understanding major themes and concepts, attendance is mandatory, she has a very friendly and helpful attitude to students in office hours regardless her German birth background.", 
            "rDate": "11/16/2013", 
            "rEasy": 2, 
            "rEasyString": "2.0", 
            "rErrorMsg": null, 
            "rHelpful": 5, 
            "rInterest": "It's my life", 
            "rOverall": 5, 
            "rOverallString": "5.0", 
            "rStatus": 1, 
            "rTextBookUse": "Yes", 
            "rWouldTakeAgain": "N/A", 
            "sId": 1112, 
            "takenForCredit": "N/A", 
            "teacher": null, 
            "teacherGrade": "N/A", 
            "teacherRatingTags": [], 
            "unUsefulGrouping": "person", 
            "usefulGrouping": "people"
        }, 
        {
            "attendance": "N/A", 
            "clarityColor": "average", 
            "easyColor": "average", 
            "helpColor": "average", 
            "helpCount": 0, 
            "id": 21209322, 
            "notHelpCount": 1, 
            "onlineClass": "", 
            "quality": "average", 
            "rClarity": 3, 
            "rClass": "HIST271", 
            "rComments": "A decent professor. Going to lecture and taking good notes is the only way to pass. Speak up as much as you can to get participation points. If you have a pretty decent grasp on this part of history then you'll be fine.", 
            "rDate": "01/04/2013", 
            "rEasy": 2, 
            "rEasyString": "2.0", 
            "rErrorMsg": null, 
            "rHelpful": 2, 
            "rInterest": "It's my life", 
            "rOverall": 2.5, 
            "rOverallString": "2.5", 
            "rStatus": 1, 
            "rTextBookUse": "Yes", 
            "rWouldTakeAgain": "N/A", 
            "sId": 1112, 
            "takenForCredit": "N/A", 
            "teacher": null, 
            "teacherGrade": "N/A", 
            "teacherRatingTags": [], 
            "unUsefulGrouping": "person", 
            "usefulGrouping": "people"
        }, 
        {
            "attendance": "N/A", 
            "clarityColor": "poor", 
            "easyColor": "average", 
            "helpColor": "poor", 
            "helpCount": 1, 
            "id": 20235250, 
            "notHelpCount": 3, 
            "onlineClass": "", 
            "quality": "poor", 
            "rClarity": 1, 
            "rClass": "HIST272", 
            "rComments": "Dr. Schneider is very liberal and makes it known.  She always talks about how conservative presidents are to blame for all of the nations problems.  She will only cover aspects of history that highlights liberal views such as welfare.  We spend 4 days on the New Deal and 1 day on WWII.  Do not take this class if you like your conservative views.", 
            "rDate": "05/09/2012", 
            "rEasy": 3, 
            "rEasyString": "3.0", 
            "rErrorMsg": null, 
            "rHelpful": 1, 
            "rInterest": "It's my life", 
            "rOverall": 1, 
            "rOverallString": "1.0", 
            "rStatus": 1, 
            "rTextBookUse": "Yes", 
            "rWouldTakeAgain": "N/A", 
            "sId": 1112, 
            "takenForCredit": "N/A", 
            "teacher": null, 
            "teacherGrade": "N/A", 
            "teacherRatingTags": [], 
            "unUsefulGrouping": "people", 
            "usefulGrouping": "person"
        }, 
        {
            "attendance": "N/A", 
            "clarityColor": "average", 
            "easyColor": "average", 
            "helpColor": "average", 
            "helpCount": 0, 
            "id": 19457767, 
            "notHelpCount": 0, 
            "onlineClass": "", 
            "quality": "average", 
            "rClarity": 2, 
            "rClass": "HIST271", 
            "rComments": "Does not reply to e-mails. Does not use technology. Knowledgable on subject material, but can be difficult to follow for notes. I only reccomend taking her class if you are really interested in U.S. history and have some prior knowledge, otherwise you'll have a really really hard time.", 
            "rDate": "12/11/2011", 
            "rEasy": 2, 
            "rEasyString": "2.0", 
            "rErrorMsg": null, 
            "rHelpful": 3, 
            "rInterest": "Sorta interested", 
            "rOverall": 2.5, 
            "rOverallString": "2.5", 
            "rStatus": 1, 
            "rTextBookUse": "Yes", 
            "rWouldTakeAgain": "N/A", 
            "sId": 1112, 
            "takenForCredit": "N/A", 
            "teacher": null, 
            "teacherGrade": "N/A", 
            "teacherRatingTags": [], 
            "unUsefulGrouping": "people", 
            "usefulGrouping": "people"
        }, 
        {
            "attendance": "N/A", 
            "clarityColor": "good", 
            "easyColor": "average", 
            "helpColor": "good", 
            "helpCount": 0, 
            "id": 19135172, 
            "notHelpCount": 1, 
            "onlineClass": "", 
            "quality": "good", 
            "rClarity": 4, 
            "rClass": "HIS200", 
            "rComments": "She is very good at what she does. She is highly educated and passionate. This is a very interesting class and she is useful and preparing me for future history classes!", 
            "rDate": "10/31/2011", 
            "rEasy": 3, 
            "rEasyString": "3.0", 
            "rErrorMsg": null, 
            "rHelpful": 4, 
            "rInterest": "Really into it", 
            "rOverall": 4, 
            "rOverallString": "4.0", 
            "rStatus": 1, 
            "rTextBookUse": "Yes", 
            "rWouldTakeAgain": "N/A", 
            "sId": 1112, 
            "takenForCredit": "N/A", 
            "teacher": null, 
            "teacherGrade": "N/A", 
            "teacherRatingTags": [], 
            "unUsefulGrouping": "person", 
            "usefulGrouping": "people"
        }, 
        {
            "attendance": "N/A", 
            "clarityColor": "poor", 
            "easyColor": "good", 
            "helpColor": "poor", 
            "helpCount": 1, 
            "id": 19010967, 
            "notHelpCount": 0, 
            "onlineClass": "", 
            "quality": "poor", 
            "rClarity": 1, 
            "rClass": "HIST200", 
            "rComments": "She rambles on and on... Pointless assignments that she grades harshly. I do NOT recommend here.", 
            "rDate": "09/20/2011", 
            "rEasy": 4, 
            "rEasyString": "4.0", 
            "rErrorMsg": null, 
            "rHelpful": 2, 
            "rInterest": "Meh", 
            "rOverall": 1.5, 
            "rOverallString": "1.5", 
            "rStatus": 1, 
            "rTextBookUse": "No", 
            "rWouldTakeAgain": "N/A", 
            "sId": 1112, 
            "takenForCredit": "N/A", 
            "teacher": null, 
            "teacherGrade": "N/A", 
            "teacherRatingTags": [], 
            "unUsefulGrouping": "people", 
            "usefulGrouping": "person"
        }, 
        {
            "attendance": "N/A", 
            "clarityColor": "poor", 
            "easyColor": "good", 
            "helpColor": "poor", 
            "helpCount": 0, 
            "id": 18573003, 
            "notHelpCount": 2, 
            "onlineClass": "", 
            "quality": "poor", 
            "rClarity": 1, 
            "rClass": "HIST272", 
            "rComments": "The worst teacher i've ever had. Very liberal, you'll learn very little about US history other than civil rights. Hard to understand, impossible transitions. Note taking is almost impossible and grading is way to harsh. A student in history always and she made me a c student.", 
            "rDate": "05/10/2011", 
            "rEasy": 5, 
            "rEasyString": "5.0", 
            "rErrorMsg": null, 
            "rHelpful": 1, 
            "rInterest": "Meh", 
            "rOverall": 1, 
            "rOverallString": "1.0", 
            "rStatus": 1, 
            "rTextBookUse": "Yes", 
            "rWouldTakeAgain": "N/A", 
            "sId": 1112, 
            "takenForCredit": "N/A", 
            "teacher": null, 
            "teacherGrade": "N/A", 
            "teacherRatingTags": [], 
            "unUsefulGrouping": "people", 
            "usefulGrouping": "people"
        }, 
        {
            "attendance": "N/A", 
            "clarityColor": "good", 
            "easyColor": "average", 
            "helpColor": "good", 
            "helpCount": 0, 
            "id": 18447608, 
            "notHelpCount": 1, 
            "onlineClass": "", 
            "quality": "good", 
            "rClarity": 4, 
            "rClass": "HIST200", 
            "rComments": "Very good teacher. She told us at the beginning of the year that she was going to grade us very hard, and for the first few assignments I found myself turning in things that normally would be A- material in a history class that received a C. However, by the end of the year I ended up writing much better and trying harder because of her teaching.", 
            "rDate": "04/21/2011", 
            "rEasy": 3, 
            "rEasyString": "3.0", 
            "rErrorMsg": null, 
            "rHelpful": 5, 
            "rInterest": "Sorta interested", 
            "rOverall": 4.5, 
            "rOverallString": "4.5", 
            "rStatus": 1, 
            "rTextBookUse": "No", 
            "rWouldTakeAgain": "N/A", 
            "sId": 1112, 
            "takenForCredit": "N/A", 
            "teacher": null, 
            "teacherGrade": "N/A", 
            "teacherRatingTags": [], 
            "unUsefulGrouping": "person", 
            "usefulGrouping": "people"
        }, 
        {
            "attendance": "N/A", 
            "clarityColor": "poor", 
            "easyColor": "good", 
            "helpColor": "poor", 
            "helpCount": 1, 
            "id": 18423675, 
            "notHelpCount": 0, 
            "onlineClass": "", 
            "quality": "poor", 
            "rClarity": 1, 
            "rClass": "HIST271", 
            "rComments": "Terrible. Don't take this professor if you want to enjoy college/history in the future.", 
            "rDate": "04/17/2011", 
            "rEasy": 5, 
            "rEasyString": "5.0", 
            "rErrorMsg": null, 
            "rHelpful": 1, 
            "rInterest": "Low", 
            "rOverall": 1, 
            "rOverallString": "1.0", 
            "rStatus": 1, 
            "rTextBookUse": "No", 
            "rWouldTakeAgain": "N/A", 
            "sId": 1112, 
            "takenForCredit": "N/A", 
            "teacher": null, 
            "teacherGrade": "N/A", 
            "teacherRatingTags": [], 
            "unUsefulGrouping": "people", 
            "usefulGrouping": "person"
        }, 
        {
            "attendance": "N/A", 
            "clarityColor": "poor", 
            "easyColor": "good", 
            "helpColor": "poor", 
            "helpCount": 1, 
            "id": 18017232, 
            "notHelpCount": 0, 
            "onlineClass": "", 
            "quality": "poor", 
            "rClarity": 1, 
            "rClass": "HIST271", 
            "rComments": "SAY NO TO THIS PROFESSOR. class is long and boring. can't understand what she says and just babbles about nothing without really teaching. grades unfairly and must be at class and participate", 
            "rDate": "12/21/2010", 
            "rEasy": 5, 
            "rEasyString": "5.0", 
            "rErrorMsg": null, 
            "rHelpful": 1, 
            "rInterest": "Meh", 
            "rOverall": 1, 
            "rOverallString": "1.0", 
            "rStatus": 1, 
            "rTextBookUse": "Yes", 
            "rWouldTakeAgain": "N/A", 
            "sId": 1112, 
            "takenForCredit": "N/A", 
            "teacher": null, 
            "teacherGrade": "N/A", 
            "teacherRatingTags": [], 
            "unUsefulGrouping": "people", 
            "usefulGrouping": "person"
        }, 
        {
            "attendance": "N/A", 
            "clarityColor": "average", 
            "easyColor": "good", 
            "helpColor": "poor", 
            "helpCount": 1, 
            "id": 17692056, 
            "notHelpCount": 0, 
            "onlineClass": "", 
            "quality": "poor", 
            "rClarity": 2, 
            "rClass": "HIST271", 
            "rComments": "She's terrible. Her tests are graded unfairly and on a ridiculous curve. She takes attendance... you can only miss 4 classes a semester. Avoid this professor", 
            "rDate": "10/26/2010", 
            "rEasy": 4, 
            "rEasyString": "4.0", 
            "rErrorMsg": null, 
            "rHelpful": 1, 
            "rInterest": "Really into it", 
            "rOverall": 1.5, 
            "rOverallString": "1.5", 
            "rStatus": 1, 
            "rTextBookUse": "Yes", 
            "rWouldTakeAgain": "N/A", 
            "sId": 1112, 
            "takenForCredit": "N/A", 
            "teacher": null, 
            "teacherGrade": "N/A", 
            "teacherRatingTags": [], 
            "unUsefulGrouping": "people", 
            "usefulGrouping": "person"
        }, 
        {
            "attendance": "N/A", 
            "clarityColor": "average", 
            "easyColor": "good", 
            "helpColor": "poor", 
            "helpCount": 1, 
            "id": 17651334, 
            "notHelpCount": 1, 
            "onlineClass": "", 
            "quality": "poor", 
            "rClarity": 2, 
            "rClass": "HIST271", 
            "rComments": "It's impossible to get a decent grade from her unless you're a brown nosing, know-it-all. She'll destroy you're writing abilities, even when she doesn't speak English. She makes annoying German noises, &quot;Ohhhhm.&quot; is her favorite.", 
            "rDate": "10/12/2010", 
            "rEasy": 4, 
            "rEasyString": "4.0", 
            "rErrorMsg": null, 
            "rHelpful": 1, 
            "rInterest": "Low", 
            "rOverall": 1.5, 
            "rOverallString": "1.5", 
            "rStatus": 1, 
            "rTextBookUse": "No", 
            "rWouldTakeAgain": "N/A", 
            "sId": 1112, 
            "takenForCredit": "N/A", 
            "teacher": null, 
            "teacherGrade": "N/A", 
            "teacherRatingTags": [], 
            "unUsefulGrouping": "person", 
            "usefulGrouping": "person"
        }, 
        {
            "attendance": "N/A", 
            "clarityColor": "average", 
            "easyColor": "good", 
            "helpColor": "average", 
            "helpCount": 0, 
            "id": 17638708, 
            "notHelpCount": 0, 
            "onlineClass": "", 
            "quality": "poor", 
            "rClarity": 2, 
            "rClass": "HIST271", 
            "rComments": "", 
            "rDate": "10/07/2010", 
            "rEasy": 4, 
            "rEasyString": "4.0", 
            "rErrorMsg": null, 
            "rHelpful": 2, 
            "rInterest": "Really into it", 
            "rOverall": 2, 
            "rOverallString": "2.0", 
            "rStatus": 1, 
            "rTextBookUse": "Yes", 
            "rWouldTakeAgain": "N/A", 
            "sId": 1112, 
            "takenForCredit": "N/A", 
            "teacher": null, 
            "teacherGrade": "N/A", 
            "teacherRatingTags": [], 
            "unUsefulGrouping": "people", 
            "usefulGrouping": "people"
        }
    ], 
    "remaining": 0
}{
    "ratings": [], 
    "remaining": 0
}{
    "ratings": [], 
    "remaining": 0
}{
    "ratings": [], 
    "remaining": 0
}{
    "ratings": [], 
    "remaining": 0
}{
    "ratings": [], 
    "remaining": 0
}{
    "ratings": [], 
    "remaining": 0
}{
    "ratings": [], 
    "remaining": 0
}{
    "ratings": [], 
    "remaining": 0
}{
    "ratings": [], 
    "remaining": 0
}{
    "ratings": [], 
    "remaining": 0
}{
    "ratings": [], 
    "remaining": 0
}{
    "ratings": [], 
    "remaining": 0
}{
    "ratings": [], 
    "remaining": 0
}{
    "ratings": [], 
    "remaining": 0
}{
    "ratings": [], 
    "remaining": 0
}{
    "ratings": [], 
    "remaining": 0
}{
    "ratings": [], 
    "remaining": 0
}