{
    "ratings": [
        {
            "attendance": "N/A", 
            "clarityColor": "good", 
            "easyColor": "good", 
            "helpColor": "good", 
            "helpCount": 1, 
            "id": 26208934, 
            "notHelpCount": 0, 
            "onlineClass": "", 
            "quality": "good", 
            "rClarity": 4, 
            "rClass": "HIS241", 
            "rComments": "You will lose points for circling wrong answers in the test. This makes it super hard for you to get an A.", 
            "rDate": "03/31/2016", 
            "rEasy": 4, 
            "rEasyString": "4.0", 
            "rErrorMsg": null, 
            "rHelpful": 4, 
            "rInterest": "N/A", 
            "rOverall": 4, 
            "rOverallString": "4.0", 
            "rStatus": 1, 
            "rTextBookUse": "Yes", 
            "rWouldTakeAgain": "N/A", 
            "sId": 1112, 
            "takenForCredit": "Yes", 
            "teacher": null, 
            "teacherGrade": "B-", 
            "teacherRatingTags": [
                "Gives good feedback", 
                "SO MANY PAPERS", 
                "Get ready to read"
            ], 
            "unUsefulGrouping": "people", 
            "usefulGrouping": "person"
        }, 
        {
            "attendance": "Mandatory", 
            "clarityColor": "good", 
            "easyColor": "poor", 
            "helpColor": "good", 
            "helpCount": 0, 
            "id": 25662078, 
            "notHelpCount": 0, 
            "onlineClass": "", 
            "quality": "good", 
            "rClarity": 4, 
            "rClass": "HIST141", 
            "rComments": "A total goofball which makes lectures interesting. If you enjoy history then this class should be an easy A, unless you're unlucky and get a terrible TA", 
            "rDate": "12/12/2015", 
            "rEasy": 1, 
            "rEasyString": "1.0", 
            "rErrorMsg": null, 
            "rHelpful": 5, 
            "rInterest": "Really into it", 
            "rOverall": 4.5, 
            "rOverallString": "4.5", 
            "rStatus": 1, 
            "rTextBookUse": "No", 
            "rWouldTakeAgain": "N/A", 
            "sId": 1112, 
            "takenForCredit": "Yes", 
            "teacher": null, 
            "teacherGrade": "N/A", 
            "teacherRatingTags": [], 
            "unUsefulGrouping": "people", 
            "usefulGrouping": "people"
        }, 
        {
            "attendance": "Mandatory", 
            "clarityColor": "good", 
            "easyColor": "poor", 
            "helpColor": "good", 
            "helpCount": 0, 
            "id": 25302508, 
            "notHelpCount": 0, 
            "onlineClass": "", 
            "quality": "good", 
            "rClarity": 5, 
            "rClass": "HIST 200", 
            "rComments": "Ralphie is the best. His classes are easy and interesting. He is super flexible with deadlines. If you get a chance to take one of his classes, do it. ", 
            "rDate": "10/27/2015", 
            "rEasy": 1, 
            "rEasyString": "1.0", 
            "rErrorMsg": null, 
            "rHelpful": 3, 
            "rInterest": "It's my life", 
            "rOverall": 4, 
            "rOverallString": "4.0", 
            "rStatus": 1, 
            "rTextBookUse": "Yes", 
            "rWouldTakeAgain": "N/A", 
            "sId": 1112, 
            "takenForCredit": "Yes", 
            "teacher": null, 
            "teacherGrade": "A", 
            "teacherRatingTags": [], 
            "unUsefulGrouping": "people", 
            "usefulGrouping": "people"
        }, 
        {
            "attendance": "Not Mandatory", 
            "clarityColor": "good", 
            "easyColor": "poor", 
            "helpColor": "good", 
            "helpCount": 0, 
            "id": 24860075, 
            "notHelpCount": 0, 
            "onlineClass": "", 
            "quality": "good", 
            "rClarity": 5, 
            "rClass": "HIST241", 
            "rComments": "Prof Mathisen's lectures are really enjoyable to sit through. I never thought I'd enjoy a history class, but I always enjoyed listening during lecture. It was easy to follow along and Prof Mathisen can be pretty funny at times. The class overall is very easy. The exams were easy and non-cumulative. Would recommend", 
            "rDate": "05/18/2015", 
            "rEasy": 1, 
            "rEasyString": "1.0", 
            "rErrorMsg": null, 
            "rHelpful": 4, 
            "rInterest": "Low", 
            "rOverall": 4.5, 
            "rOverallString": "4.5", 
            "rStatus": 1, 
            "rTextBookUse": "No", 
            "rWouldTakeAgain": "N/A", 
            "sId": 1112, 
            "takenForCredit": "Yes", 
            "teacher": null, 
            "teacherGrade": "A", 
            "teacherRatingTags": [
                "Hilarious", 
                "Clear grading criteria", 
                "Amazing lectures"
            ], 
            "unUsefulGrouping": "people", 
            "usefulGrouping": "people"
        }, 
        {
            "attendance": "Mandatory", 
            "clarityColor": "good", 
            "easyColor": "poor", 
            "helpColor": "good", 
            "helpCount": 0, 
            "id": 23088131, 
            "notHelpCount": 0, 
            "onlineClass": "", 
            "quality": "good", 
            "rClarity": 5, 
            "rClass": "HIST200", 
            "rComments": "Such an enthusiastic teacher. Very positive attitude. Not a big history fan (I'm an econ major) but this class made me enjoy history 100% more than I normally would. Learned so much!!", 
            "rDate": "04/23/2014", 
            "rEasy": 1, 
            "rEasyString": "1.0", 
            "rErrorMsg": null, 
            "rHelpful": 5, 
            "rInterest": "Really into it", 
            "rOverall": 5, 
            "rOverallString": "5.0", 
            "rStatus": 1, 
            "rTextBookUse": "Yes", 
            "rWouldTakeAgain": "N/A", 
            "sId": 1112, 
            "takenForCredit": "N/A", 
            "teacher": null, 
            "teacherGrade": "A", 
            "teacherRatingTags": [], 
            "unUsefulGrouping": "people", 
            "usefulGrouping": "people"
        }, 
        {
            "attendance": "N/A", 
            "clarityColor": "good", 
            "easyColor": "average", 
            "helpColor": "good", 
            "helpCount": 0, 
            "id": 18484810, 
            "notHelpCount": 0, 
            "onlineClass": "", 
            "quality": "good", 
            "rClarity": 4, 
            "rClass": "CLCV116", 
            "rComments": "He is great! Very animated and likes to dance during lectures.  One essay, that can be rewritten later for a higher grade. Lets the class choose the type of exam layout for the semester.  Class is mandatory as it is prorated and can be used to substitue your lowest exam grade!", 
            "rDate": "04/28/2011", 
            "rEasy": 2, 
            "rEasyString": "2.0", 
            "rErrorMsg": null, 
            "rHelpful": 4, 
            "rInterest": "Really into it", 
            "rOverall": 4, 
            "rOverallString": "4.0", 
            "rStatus": 1, 
            "rTextBookUse": "No", 
            "rWouldTakeAgain": "N/A", 
            "sId": 1112, 
            "takenForCredit": "N/A", 
            "teacher": null, 
            "teacherGrade": "N/A", 
            "teacherRatingTags": [], 
            "unUsefulGrouping": "people", 
            "usefulGrouping": "people"
        }, 
        {
            "attendance": "N/A", 
            "clarityColor": "good", 
            "easyColor": "poor", 
            "helpColor": "good", 
            "helpCount": 0, 
            "id": 18375889, 
            "notHelpCount": 0, 
            "onlineClass": "", 
            "quality": "good", 
            "rClarity": 5, 
            "rClass": "CLCV116", 
            "rComments": "best class ever", 
            "rDate": "04/07/2011", 
            "rEasy": 1, 
            "rEasyString": "1.0", 
            "rErrorMsg": null, 
            "rHelpful": 5, 
            "rInterest": "It's my life", 
            "rOverall": 5, 
            "rOverallString": "5.0", 
            "rStatus": 1, 
            "rTextBookUse": "No", 
            "rWouldTakeAgain": "N/A", 
            "sId": 12091, 
            "takenForCredit": "N/A", 
            "teacher": null, 
            "teacherGrade": "N/A", 
            "teacherRatingTags": [], 
            "unUsefulGrouping": "people", 
            "usefulGrouping": "people"
        }, 
        {
            "attendance": "N/A", 
            "clarityColor": "good", 
            "easyColor": "poor", 
            "helpColor": "good", 
            "helpCount": 3, 
            "id": 16734195, 
            "notHelpCount": 0, 
            "onlineClass": "", 
            "quality": "good", 
            "rClarity": 5, 
            "rClass": "HIST241", 
            "rComments": "Need a West and/or Hum&#63;  Then definitely take his hist241.  He lets the class decide the format of the exams. Really easy exams and the last one is non-comp.(final) and one short paper(this is what you need the thin book for).  Lets you redo paper if you score lower than an A.  His lectures captured my attention :)", 
            "rDate": "01/16/2010", 
            "rEasy": 1, 
            "rEasyString": "1.0", 
            "rErrorMsg": null, 
            "rHelpful": 5, 
            "rInterest": "Sorta interested", 
            "rOverall": 5, 
            "rOverallString": "5.0", 
            "rStatus": 1, 
            "rTextBookUse": "No", 
            "rWouldTakeAgain": "N/A", 
            "sId": 1112, 
            "takenForCredit": "N/A", 
            "teacher": null, 
            "teacherGrade": "N/A", 
            "teacherRatingTags": [], 
            "unUsefulGrouping": "people", 
            "usefulGrouping": "people"
        }, 
        {
            "attendance": "N/A", 
            "clarityColor": "good", 
            "easyColor": "poor", 
            "helpColor": "good", 
            "helpCount": 0, 
            "id": 16326990, 
            "notHelpCount": 0, 
            "onlineClass": "", 
            "quality": "good", 
            "rClarity": 4, 
            "rClass": "HIS241", 
            "rComments": "one of the easiest classes i've ever taken.  Great professor, knows a ton...kept me interested with stories", 
            "rDate": "11/06/2009", 
            "rEasy": 1, 
            "rEasyString": "1.0", 
            "rErrorMsg": null, 
            "rHelpful": 4, 
            "rInterest": "Really into it", 
            "rOverall": 4, 
            "rOverallString": "4.0", 
            "rStatus": 1, 
            "rTextBookUse": "No", 
            "rWouldTakeAgain": "N/A", 
            "sId": 1112, 
            "takenForCredit": "N/A", 
            "teacher": null, 
            "teacherGrade": "N/A", 
            "teacherRatingTags": [], 
            "unUsefulGrouping": "people", 
            "usefulGrouping": "people"
        }, 
        {
            "attendance": "N/A", 
            "clarityColor": "good", 
            "easyColor": "poor", 
            "helpColor": "good", 
            "helpCount": 0, 
            "id": 16298400, 
            "notHelpCount": 0, 
            "onlineClass": "", 
            "quality": "good", 
            "rClarity": 5, 
            "rClass": "HIST241", 
            "rComments": "Ralphie is awesome! The topic itself isn't always interesting, but Prof Mathisen is good at teaching it. Funny, nice, very helpful, EXTREMELY easy, lets the class pick the type of exam, only one paper and can redo it for a better grade.", 
            "rDate": "11/02/2009", 
            "rEasy": 1, 
            "rEasyString": "1.0", 
            "rErrorMsg": null, 
            "rHelpful": 5, 
            "rInterest": "Sorta interested", 
            "rOverall": 5, 
            "rOverallString": "5.0", 
            "rStatus": 1, 
            "rTextBookUse": "No", 
            "rWouldTakeAgain": "N/A", 
            "sId": 1112, 
            "takenForCredit": "N/A", 
            "teacher": null, 
            "teacherGrade": "N/A", 
            "teacherRatingTags": [], 
            "unUsefulGrouping": "people", 
            "usefulGrouping": "people"
        }, 
        {
            "attendance": "N/A", 
            "clarityColor": "good", 
            "easyColor": "poor", 
            "helpColor": "good", 
            "helpCount": 0, 
            "id": 16106205, 
            "notHelpCount": 0, 
            "onlineClass": "", 
            "quality": "good", 
            "rClarity": 5, 
            "rClass": "HIST241", 
            "rComments": "I learned a lot from his class. He is a great teacher and kept people interested in coming to class. He lets the class pick the format of the test, and everything on it is in the study guide he gives you, so getting an A is no problem. We only had to write on paper, which wasn't to difficult.", 
            "rDate": "08/10/2009", 
            "rEasy": 1, 
            "rEasyString": "1.0", 
            "rErrorMsg": null, 
            "rHelpful": 5, 
            "rInterest": "Sorta interested", 
            "rOverall": 5, 
            "rOverallString": "5.0", 
            "rStatus": 1, 
            "rTextBookUse": "No", 
            "rWouldTakeAgain": "N/A", 
            "sId": 1112, 
            "takenForCredit": "N/A", 
            "teacher": null, 
            "teacherGrade": "N/A", 
            "teacherRatingTags": [], 
            "unUsefulGrouping": "people", 
            "usefulGrouping": "people"
        }, 
        {
            "attendance": "N/A", 
            "clarityColor": "good", 
            "easyColor": "poor", 
            "helpColor": "good", 
            "helpCount": 0, 
            "id": 15807454, 
            "notHelpCount": 0, 
            "onlineClass": "", 
            "quality": "good", 
            "rClarity": 5, 
            "rClass": "HIST241", 
            "rComments": "Prof. Mathiesen is awesome and lectures are pretty interesting.", 
            "rDate": "05/10/2009", 
            "rEasy": 1, 
            "rEasyString": "1.0", 
            "rErrorMsg": null, 
            "rHelpful": 4, 
            "rInterest": "Really into it", 
            "rOverall": 4.5, 
            "rOverallString": "4.5", 
            "rStatus": 1, 
            "rTextBookUse": "No", 
            "rWouldTakeAgain": "N/A", 
            "sId": 1112, 
            "takenForCredit": "N/A", 
            "teacher": null, 
            "teacherGrade": "N/A", 
            "teacherRatingTags": [], 
            "unUsefulGrouping": "people", 
            "usefulGrouping": "people"
        }, 
        {
            "attendance": "N/A", 
            "clarityColor": "good", 
            "easyColor": "poor", 
            "helpColor": "good", 
            "helpCount": 1, 
            "id": 15799032, 
            "notHelpCount": 0, 
            "onlineClass": "", 
            "quality": "good", 
            "rClarity": 5, 
            "rClass": "HIST241", 
            "rComments": "Professor Mathisen is a character. The class is pretty easy if you go. Lecture are somewhat interesting and pretty informative. All of the test questions come from lecture, no need to read anything. He allows you to vote on the format of the tests. He also lets you substitute your attendance for your lowest test grade. Only 1 short paper required.", 
            "rDate": "05/08/2009", 
            "rEasy": 1, 
            "rEasyString": "1.0", 
            "rErrorMsg": null, 
            "rHelpful": 4, 
            "rInterest": "Really into it", 
            "rOverall": 4.5, 
            "rOverallString": "4.5", 
            "rStatus": 1, 
            "rTextBookUse": "No", 
            "rWouldTakeAgain": "N/A", 
            "sId": 1112, 
            "takenForCredit": "N/A", 
            "teacher": null, 
            "teacherGrade": "N/A", 
            "teacherRatingTags": [], 
            "unUsefulGrouping": "people", 
            "usefulGrouping": "person"
        }, 
        {
            "attendance": "N/A", 
            "clarityColor": "good", 
            "easyColor": "poor", 
            "helpColor": "good", 
            "helpCount": 0, 
            "id": 15649626, 
            "notHelpCount": 0, 
            "onlineClass": "", 
            "quality": "good", 
            "rClarity": 5, 
            "rClass": "HIST241", 
            "rComments": "Ralphie rocks!  He's such a goofball, but he's also really informative.  The class might not be the best if you're not really interested in Roman history, but if you are, take it!  I learned so much without ever even having to open the book.", 
            "rDate": "04/14/2009", 
            "rEasy": 1, 
            "rEasyString": "1.0", 
            "rErrorMsg": null, 
            "rHelpful": 4, 
            "rInterest": "Really into it", 
            "rOverall": 4.5, 
            "rOverallString": "4.5", 
            "rStatus": 1, 
            "rTextBookUse": "No", 
            "rWouldTakeAgain": "N/A", 
            "sId": 1112, 
            "takenForCredit": "N/A", 
            "teacher": null, 
            "teacherGrade": "N/A", 
            "teacherRatingTags": [], 
            "unUsefulGrouping": "people", 
            "usefulGrouping": "people"
        }, 
        {
            "attendance": "N/A", 
            "clarityColor": "good", 
            "easyColor": "poor", 
            "helpColor": "good", 
            "helpCount": 0, 
            "id": 15107789, 
            "notHelpCount": 0, 
            "onlineClass": "", 
            "quality": "good", 
            "rClarity": 4, 
            "rClass": "HIST141", 
            "rComments": "This is my 3rd class with Ralphie and I HIGHLY recommend him. If you try and &quot;give him something&quot; in terms of assignments, you will do well. His laid back teaching style really helped me learn and maintain an interest in Roman History. I *heart* you, Ralphie!", 
            "rDate": "12/04/2008", 
            "rEasy": 1, 
            "rEasyString": "1.0", 
            "rErrorMsg": null, 
            "rHelpful": 5, 
            "rInterest": "Really into it", 
            "rOverall": 4.5, 
            "rOverallString": "4.5", 
            "rStatus": 1, 
            "rTextBookUse": "No", 
            "rWouldTakeAgain": "N/A", 
            "sId": 1112, 
            "takenForCredit": "N/A", 
            "teacher": null, 
            "teacherGrade": "N/A", 
            "teacherRatingTags": [], 
            "unUsefulGrouping": "people", 
            "usefulGrouping": "people"
        }, 
        {
            "attendance": "N/A", 
            "clarityColor": "good", 
            "easyColor": "average", 
            "helpColor": "good", 
            "helpCount": 0, 
            "id": 14373757, 
            "notHelpCount": 0, 
            "onlineClass": "", 
            "quality": "good", 
            "rClarity": 4, 
            "rClass": "HIST141", 
            "rComments": "Prof. Mathison is a interesting teacher. The lecture follows his notes very closely. His tests are multiple choice multiple answer.", 
            "rDate": "04/30/2008", 
            "rEasy": 3, 
            "rEasyString": "3.0", 
            "rErrorMsg": null, 
            "rHelpful": 4, 
            "rInterest": "Really into it", 
            "rOverall": 4, 
            "rOverallString": "4.0", 
            "rStatus": 1, 
            "rTextBookUse": "Yes", 
            "rWouldTakeAgain": "N/A", 
            "sId": 1112, 
            "takenForCredit": "N/A", 
            "teacher": null, 
            "teacherGrade": "N/A", 
            "teacherRatingTags": [], 
            "unUsefulGrouping": "people", 
            "usefulGrouping": "people"
        }, 
        {
            "attendance": "N/A", 
            "clarityColor": "good", 
            "easyColor": "poor", 
            "helpColor": "good", 
            "helpCount": 0, 
            "id": 14222391, 
            "notHelpCount": 0, 
            "onlineClass": "", 
            "quality": "good", 
            "rClarity": 5, 
            "rClass": "HIST141", 
            "rComments": "This guy is hilarious. He's a very interesting teacher, too, and his overheads in lecture keep the outline of the subject matter, too. The TA I have is nice and fair with her grading.", 
            "rDate": "03/31/2008", 
            "rEasy": 1, 
            "rEasyString": "1.0", 
            "rErrorMsg": null, 
            "rHelpful": 5, 
            "rInterest": "Sorta interested", 
            "rOverall": 5, 
            "rOverallString": "5.0", 
            "rStatus": 1, 
            "rTextBookUse": "Yes", 
            "rWouldTakeAgain": "N/A", 
            "sId": 1112, 
            "takenForCredit": "N/A", 
            "teacher": null, 
            "teacherGrade": "N/A", 
            "teacherRatingTags": [], 
            "unUsefulGrouping": "people", 
            "usefulGrouping": "people"
        }, 
        {
            "attendance": "N/A", 
            "clarityColor": "good", 
            "easyColor": "average", 
            "helpColor": "good", 
            "helpCount": 0, 
            "id": 12617677, 
            "notHelpCount": 0, 
            "onlineClass": "", 
            "quality": "good", 
            "rClarity": 4, 
            "rClass": "HIST443", 
            "rComments": "I took 3 classes with Ralphie and loved every one.  Easy grader, easy assignments, and all you have to do is put up with some bad jokes.  He is very enthusiastic and helpful, even writing me a letter of recommendation for law school.  His advanced courses are better than his 200 level courses as they are more individualized.", 
            "rDate": "12/15/2006", 
            "rEasy": 2, 
            "rEasyString": "2.0", 
            "rErrorMsg": null, 
            "rHelpful": 4, 
            "rInterest": "Really into it", 
            "rOverall": 4, 
            "rOverallString": "4.0", 
            "rStatus": 1, 
            "rTextBookUse": "No", 
            "rWouldTakeAgain": "N/A", 
            "sId": 1112, 
            "takenForCredit": "N/A", 
            "teacher": null, 
            "teacherGrade": "N/A", 
            "teacherRatingTags": [], 
            "unUsefulGrouping": "people", 
            "usefulGrouping": "people"
        }, 
        {
            "attendance": "N/A", 
            "clarityColor": "average", 
            "easyColor": "average", 
            "helpColor": "average", 
            "helpCount": 0, 
            "id": 12434995, 
            "notHelpCount": 0, 
            "onlineClass": "", 
            "quality": "poor", 
            "rClarity": 3, 
            "rClass": "HIST241", 
            "rComments": "He is very unprofessional and unhelpful at office hours, the TA for the class was an incredibly hard grader.", 
            "rDate": "11/16/2006", 
            "rEasy": 2, 
            "rEasyString": "2.0", 
            "rErrorMsg": null, 
            "rHelpful": 1, 
            "rInterest": "Really into it", 
            "rOverall": 2, 
            "rOverallString": "2.0", 
            "rStatus": 1, 
            "rTextBookUse": "No", 
            "rWouldTakeAgain": "N/A", 
            "sId": 1112, 
            "takenForCredit": "N/A", 
            "teacher": null, 
            "teacherGrade": "N/A", 
            "teacherRatingTags": [], 
            "unUsefulGrouping": "people", 
            "usefulGrouping": "people"
        }, 
        {
            "attendance": "N/A", 
            "clarityColor": "poor", 
            "easyColor": "average", 
            "helpColor": "poor", 
            "helpCount": 0, 
            "id": 12364553, 
            "notHelpCount": 0, 
            "onlineClass": "", 
            "quality": "poor", 
            "rClarity": 1, 
            "rClass": "HIST241", 
            "rComments": "Very unprofessional-anwsers cell phone in class.  Not clear test instructions.  Test grader is a bit**  I hated this class", 
            "rDate": "11/06/2006", 
            "rEasy": 3, 
            "rEasyString": "3.0", 
            "rErrorMsg": null, 
            "rHelpful": 1, 
            "rInterest": "Sorta interested", 
            "rOverall": 1, 
            "rOverallString": "1.0", 
            "rStatus": 1, 
            "rTextBookUse": "No", 
            "rWouldTakeAgain": "N/A", 
            "sId": 1112, 
            "takenForCredit": "N/A", 
            "teacher": null, 
            "teacherGrade": "N/A", 
            "teacherRatingTags": [], 
            "unUsefulGrouping": "people", 
            "usefulGrouping": "people"
        }
    ], 
    "remaining": 4
}{
    "ratings": [
        {
            "attendance": "N/A", 
            "clarityColor": "average", 
            "easyColor": "poor", 
            "helpColor": "average", 
            "helpCount": 1, 
            "id": 11286344, 
            "notHelpCount": 0, 
            "onlineClass": "", 
            "quality": "average", 
            "rClarity": 3, 
            "rClass": "HIST442", 
            "rComments": "funny guy, extremely easy grader. can honestly say i learned very little and skated by with an A.", 
            "rDate": "01/01/2006", 
            "rEasy": 1, 
            "rEasyString": "1.0", 
            "rErrorMsg": null, 
            "rHelpful": 3, 
            "rInterest": "Sorta interested", 
            "rOverall": 3, 
            "rOverallString": "3.0", 
            "rStatus": 1, 
            "rTextBookUse": "N/A", 
            "rWouldTakeAgain": "N/A", 
            "sId": 1112, 
            "takenForCredit": "N/A", 
            "teacher": null, 
            "teacherGrade": "N/A", 
            "teacherRatingTags": [], 
            "unUsefulGrouping": "people", 
            "usefulGrouping": "person"
        }, 
        {
            "attendance": "N/A", 
            "clarityColor": "good", 
            "easyColor": "poor", 
            "helpColor": "good", 
            "helpCount": 0, 
            "id": 10022956, 
            "notHelpCount": 0, 
            "onlineClass": "", 
            "quality": "good", 
            "rClarity": 5, 
            "rClass": "HIST241", 
            "rComments": "Great teacher, enthusiastic and has a ton of stories to relate to the subject. Not too hard of a class and overall amazing. Wears great hats to class too. overall goofball and likes to just take fun tangents but still gets the information through.", 
            "rDate": "07/13/2005", 
            "rEasy": 1, 
            "rEasyString": "1.0", 
            "rErrorMsg": null, 
            "rHelpful": 5, 
            "rInterest": "It's my life", 
            "rOverall": 5, 
            "rOverallString": "5.0", 
            "rStatus": 1, 
            "rTextBookUse": "N/A", 
            "rWouldTakeAgain": "N/A", 
            "sId": 1112, 
            "takenForCredit": "N/A", 
            "teacher": null, 
            "teacherGrade": "N/A", 
            "teacherRatingTags": [], 
            "unUsefulGrouping": "people", 
            "usefulGrouping": "people"
        }, 
        {
            "attendance": "N/A", 
            "clarityColor": "good", 
            "easyColor": "poor", 
            "helpColor": "good", 
            "helpCount": 0, 
            "id": 3844394, 
            "notHelpCount": 0, 
            "onlineClass": "", 
            "quality": "good", 
            "rClarity": 5, 
            "rClass": "HIST241", 
            "rComments": "Very friendly, his class itself was as interesting as history gets.  He tends to talk too much about Roman coins, so mush so that it became funny.  Also, at 90 minutes long non-history majors may not be able to sit for the entire session, but the easiness of the class makes it worth while.", 
            "rDate": "05/12/2005", 
            "rEasy": 1, 
            "rEasyString": "1.0", 
            "rErrorMsg": null, 
            "rHelpful": 4, 
            "rInterest": "Really into it", 
            "rOverall": 4.5, 
            "rOverallString": "4.5", 
            "rStatus": 1, 
            "rTextBookUse": "N/A", 
            "rWouldTakeAgain": "N/A", 
            "sId": 1112, 
            "takenForCredit": "N/A", 
            "teacher": null, 
            "teacherGrade": "N/A", 
            "teacherRatingTags": [], 
            "unUsefulGrouping": "people", 
            "usefulGrouping": "people"
        }, 
        {
            "attendance": "N/A", 
            "clarityColor": "good", 
            "easyColor": "poor", 
            "helpColor": "good", 
            "helpCount": 1, 
            "id": 2965541, 
            "notHelpCount": 0, 
            "onlineClass": "", 
            "quality": "good", 
            "rClarity": 5, 
            "rClass": "HIST241", 
            "rComments": "Excellent teacher. Very funny. Made the class much more interesting. Tests are easy (He leaves it up to the class to decide the format).", 
            "rDate": "12/09/2004", 
            "rEasy": 1, 
            "rEasyString": "1.0", 
            "rErrorMsg": null, 
            "rHelpful": 5, 
            "rInterest": "Really into it", 
            "rOverall": 5, 
            "rOverallString": "5.0", 
            "rStatus": 1, 
            "rTextBookUse": "N/A", 
            "rWouldTakeAgain": "N/A", 
            "sId": 1112, 
            "takenForCredit": "N/A", 
            "teacher": null, 
            "teacherGrade": "N/A", 
            "teacherRatingTags": [], 
            "unUsefulGrouping": "people", 
            "usefulGrouping": "person"
        }
    ], 
    "remaining": 0
}{
    "ratings": [], 
    "remaining": 0
}{
    "ratings": [], 
    "remaining": 0
}{
    "ratings": [], 
    "remaining": 0
}{
    "ratings": [], 
    "remaining": 0
}{
    "ratings": [], 
    "remaining": 0
}{
    "ratings": [], 
    "remaining": 0
}{
    "ratings": [], 
    "remaining": 0
}{
    "ratings": [], 
    "remaining": 0
}{
    "ratings": [], 
    "remaining": 0
}{
    "ratings": [], 
    "remaining": 0
}{
    "ratings": [], 
    "remaining": 0
}{
    "ratings": [], 
    "remaining": 0
}{
    "ratings": [], 
    "remaining": 0
}{
    "ratings": [], 
    "remaining": 0
}{
    "ratings": [], 
    "remaining": 0
}{
    "ratings": [], 
    "remaining": 0
}