{
    "ratings": [
        {
            "attendance": "N/A", 
            "clarityColor": "good", 
            "easyColor": "average", 
            "helpColor": "good", 
            "helpCount": 0, 
            "id": 18644218, 
            "notHelpCount": 0, 
            "onlineClass": "", 
            "quality": "good", 
            "rClarity": 5, 
            "rClass": "EIL460", 
            "rComments": "This class was honestly my favorite class during the semester.I learned so much from Prof. Davidson - he explained concepts clearly and well. We grouped up and designed test of our own and Davidson provided lots of great feedback. Same with the three papers we wrote throughout the class. Overall, I learned so much throughout the class.", 
            "rDate": "05/21/2011", 
            "rEasy": 2, 
            "rEasyString": "2.0", 
            "rErrorMsg": null, 
            "rHelpful": 5, 
            "rInterest": "Really into it", 
            "rOverall": 5, 
            "rOverallString": "5.0", 
            "rStatus": 1, 
            "rTextBookUse": "Yes", 
            "rWouldTakeAgain": "N/A", 
            "sId": 1112, 
            "takenForCredit": "N/A", 
            "teacher": null, 
            "teacherGrade": "N/A", 
            "teacherRatingTags": [], 
            "unUsefulGrouping": "people", 
            "usefulGrouping": "people"
        }, 
        {
            "attendance": "N/A", 
            "clarityColor": "average", 
            "easyColor": "average", 
            "helpColor": "poor", 
            "helpCount": 0, 
            "id": 17666484, 
            "notHelpCount": 0, 
            "onlineClass": "", 
            "quality": "poor", 
            "rClarity": 2, 
            "rClass": "EIL422", 
            "rComments": "More like self-study; activities in class not related to material; extremely vague explanations (if at all); ridiculous lecture on writing about grammar (use italics, use bullet points).  Complete waste of time, but mandatory course.", 
            "rDate": "10/18/2010", 
            "rEasy": 2, 
            "rEasyString": "2.0", 
            "rErrorMsg": null, 
            "rHelpful": 1, 
            "rInterest": "Low", 
            "rOverall": 1.5, 
            "rOverallString": "1.5", 
            "rStatus": 1, 
            "rTextBookUse": "No", 
            "rWouldTakeAgain": "N/A", 
            "sId": 1112, 
            "takenForCredit": "N/A", 
            "teacher": null, 
            "teacherGrade": "N/A", 
            "teacherRatingTags": [], 
            "unUsefulGrouping": "people", 
            "usefulGrouping": "people"
        }, 
        {
            "attendance": "N/A", 
            "clarityColor": "average", 
            "easyColor": "average", 
            "helpColor": "average", 
            "helpCount": 0, 
            "id": 14763541, 
            "notHelpCount": 0, 
            "onlineClass": "", 
            "quality": "average", 
            "rClarity": 3, 
            "rClass": "EIL460", 
            "rComments": "Most of the in-class time was a bit wasted, but the book is good and the papers helped me think about testing and assessment.", 
            "rDate": "08/21/2008", 
            "rEasy": 3, 
            "rEasyString": "3.0", 
            "rErrorMsg": null, 
            "rHelpful": 2, 
            "rInterest": "Low", 
            "rOverall": 2.5, 
            "rOverallString": "2.5", 
            "rStatus": 1, 
            "rTextBookUse": "Yes", 
            "rWouldTakeAgain": "N/A", 
            "sId": 1112, 
            "takenForCredit": "N/A", 
            "teacher": null, 
            "teacherGrade": "N/A", 
            "teacherRatingTags": [], 
            "unUsefulGrouping": "people", 
            "usefulGrouping": "people"
        }
    ], 
    "remaining": 0
}{
    "ratings": [], 
    "remaining": 0
}{
    "ratings": [], 
    "remaining": 0
}{
    "ratings": [], 
    "remaining": 0
}{
    "ratings": [], 
    "remaining": 0
}{
    "ratings": [], 
    "remaining": 0
}{
    "ratings": [], 
    "remaining": 0
}{
    "ratings": [], 
    "remaining": 0
}{
    "ratings": [], 
    "remaining": 0
}{
    "ratings": [], 
    "remaining": 0
}{
    "ratings": [], 
    "remaining": 0
}{
    "ratings": [], 
    "remaining": 0
}{
    "ratings": [], 
    "remaining": 0
}{
    "ratings": [], 
    "remaining": 0
}{
    "ratings": [], 
    "remaining": 0
}{
    "ratings": [], 
    "remaining": 0
}{
    "ratings": [], 
    "remaining": 0
}{
    "ratings": [], 
    "remaining": 0
}