{
    "ratings": [
        {
            "attendance": "Mandatory", 
            "clarityColor": "good", 
            "easyColor": "good", 
            "helpColor": "good", 
            "helpCount": 1, 
            "id": 24547442, 
            "notHelpCount": 0, 
            "onlineClass": "", 
            "quality": "good", 
            "rClarity": 5, 
            "rClass": "MCB150", 
            "rComments": "Mehrtens is a hall-of-fame lecturer. He never says \"um\" or \"like.\" Everything is clear and deliberate, like he has his lectures memorized in his head. That being said, the class was not easy for me, and I highly suggest not skipping. Tests are difficult, even if you study diligently, but his grading scale gives you a legit chance to do well.", 
            "rDate": "04/05/2015", 
            "rEasy": 4, 
            "rEasyString": "4.0", 
            "rErrorMsg": null, 
            "rHelpful": 4, 
            "rInterest": "Really into it", 
            "rOverall": 4.5, 
            "rOverallString": "4.5", 
            "rStatus": 1, 
            "rTextBookUse": "Yes", 
            "rWouldTakeAgain": "N/A", 
            "sId": 1112, 
            "takenForCredit": "Yes", 
            "teacher": null, 
            "teacherGrade": "B-", 
            "teacherRatingTags": [], 
            "unUsefulGrouping": "people", 
            "usefulGrouping": "person"
        }, 
        {
            "attendance": "Mandatory", 
            "clarityColor": "good", 
            "easyColor": "average", 
            "helpColor": "good", 
            "helpCount": 0, 
            "id": 24397041, 
            "notHelpCount": 0, 
            "onlineClass": "", 
            "quality": "good", 
            "rClarity": 4, 
            "rClass": "MCB150", 
            "rComments": "Great lecturer, extremely difficult exams. Be sure to utilize office hours on a weekly or at least bi-weekly basis if you want an A. Ask questions as often as possible.", 
            "rDate": "02/19/2015", 
            "rEasy": 3, 
            "rEasyString": "3.0", 
            "rErrorMsg": null, 
            "rHelpful": 5, 
            "rInterest": "Really into it", 
            "rOverall": 4.5, 
            "rOverallString": "4.5", 
            "rStatus": 1, 
            "rTextBookUse": "Yes", 
            "rWouldTakeAgain": "N/A", 
            "sId": 1112, 
            "takenForCredit": "Yes", 
            "teacher": null, 
            "teacherGrade": "B", 
            "teacherRatingTags": [
                "Skip class? You won't pass.", 
                "Tough Grader", 
                "Amazing lectures"
            ], 
            "unUsefulGrouping": "people", 
            "usefulGrouping": "people"
        }, 
        {
            "attendance": "Mandatory", 
            "clarityColor": "good", 
            "easyColor": "good", 
            "helpColor": "good", 
            "helpCount": 3, 
            "id": 24321156, 
            "notHelpCount": 0, 
            "onlineClass": "", 
            "quality": "good", 
            "rClarity": 4, 
            "rClass": "MCB150", 
            "rComments": "Brad is a great lecturer who explains the material well. Must show up to lectures or you will be lost. Don't focus on the textbook. record the lectures and listen to the lectures again before the exam and you should be okay.", 
            "rDate": "01/22/2015", 
            "rEasy": 4, 
            "rEasyString": "4.0", 
            "rErrorMsg": null, 
            "rHelpful": 4, 
            "rInterest": "Sorta interested", 
            "rOverall": 4, 
            "rOverallString": "4.0", 
            "rStatus": 1, 
            "rTextBookUse": "No", 
            "rWouldTakeAgain": "N/A", 
            "sId": 1112, 
            "takenForCredit": "Yes", 
            "teacher": null, 
            "teacherGrade": "N/A", 
            "teacherRatingTags": [
                "Tough Grader", 
                "Skip class? You won't pass."
            ], 
            "unUsefulGrouping": "people", 
            "usefulGrouping": "people"
        }, 
        {
            "attendance": "N/A", 
            "clarityColor": "good", 
            "easyColor": "good", 
            "helpColor": "good", 
            "helpCount": 2, 
            "id": 24298820, 
            "notHelpCount": 0, 
            "onlineClass": "", 
            "quality": "good", 
            "rClarity": 5, 
            "rClass": "MCB150", 
            "rComments": "Mehrtens made \"the study of life\" very lively with his natural zeal for teaching. He will make you work for it, but it is totally worth it if you wish to go down the pre-med track. Office Hours is where you can really get to know the material from Mehrtens himself! Bottom line, he will really teach you biology like no other professor. 3 Thumbs Up!", 
            "rDate": "01/16/2015", 
            "rEasy": 4, 
            "rEasyString": "4.0", 
            "rErrorMsg": null, 
            "rHelpful": 4, 
            "rInterest": "It's my life", 
            "rOverall": 4.5, 
            "rOverallString": "4.5", 
            "rStatus": 1, 
            "rTextBookUse": "Yes", 
            "rWouldTakeAgain": "N/A", 
            "sId": 1112, 
            "takenForCredit": "Yes", 
            "teacher": null, 
            "teacherGrade": "N/A", 
            "teacherRatingTags": [
                "CARES ABOUT STUDENTS", 
                "Amazing lectures", 
                "Skip class? You won't pass."
            ], 
            "unUsefulGrouping": "people", 
            "usefulGrouping": "people"
        }, 
        {
            "attendance": "Mandatory", 
            "clarityColor": "good", 
            "easyColor": "good", 
            "helpColor": "good", 
            "helpCount": 2, 
            "id": 24204761, 
            "notHelpCount": 0, 
            "onlineClass": "", 
            "quality": "good", 
            "rClarity": 4, 
            "rClass": "MCB150", 
            "rComments": "Majoring in IB so not all that interested, but Brad made the class a lot of fun. Brutal tests, but great grading scale! Didn't love the material but Brad made it the best it could possibly be.", 
            "rDate": "12/30/2014", 
            "rEasy": 4, 
            "rEasyString": "4.0", 
            "rErrorMsg": null, 
            "rHelpful": 5, 
            "rInterest": "Low", 
            "rOverall": 4.5, 
            "rOverallString": "4.5", 
            "rStatus": 1, 
            "rTextBookUse": "Yes", 
            "rWouldTakeAgain": "N/A", 
            "sId": 1112, 
            "takenForCredit": "Yes", 
            "teacher": null, 
            "teacherGrade": "A-", 
            "teacherRatingTags": [
                "CARES ABOUT STUDENTS", 
                "Tough Grader", 
                "Respected by students"
            ], 
            "unUsefulGrouping": "people", 
            "usefulGrouping": "people"
        }, 
        {
            "attendance": "Not Mandatory", 
            "clarityColor": "good", 
            "easyColor": "good", 
            "helpColor": "good", 
            "helpCount": 1, 
            "id": 24073684, 
            "notHelpCount": 0, 
            "onlineClass": "", 
            "quality": "good", 
            "rClarity": 5, 
            "rClass": "MCB150", 
            "rComments": "Brad is a great professor who really cares about students. There is a LOT of content that is covered in this course. If you want to do well, you MUST show up to lecture and do the assigned readings. Brad presents information in a very clear manner during his lectures and he is always available to help. That being said, this class is not an easy A.", 
            "rDate": "12/14/2014", 
            "rEasy": 4, 
            "rEasyString": "4.0", 
            "rErrorMsg": null, 
            "rHelpful": 5, 
            "rInterest": "It's my life", 
            "rOverall": 5, 
            "rOverallString": "5.0", 
            "rStatus": 1, 
            "rTextBookUse": "Yes", 
            "rWouldTakeAgain": "N/A", 
            "sId": 1112, 
            "takenForCredit": "Yes", 
            "teacher": null, 
            "teacherGrade": "A", 
            "teacherRatingTags": [
                "Respected by students", 
                "CARES ABOUT STUDENTS", 
                "Skip class? You won't pass."
            ], 
            "unUsefulGrouping": "people", 
            "usefulGrouping": "person"
        }, 
        {
            "attendance": "N/A", 
            "clarityColor": "good", 
            "easyColor": "good", 
            "helpColor": "good", 
            "helpCount": 2, 
            "id": 23962229, 
            "notHelpCount": 0, 
            "onlineClass": "", 
            "quality": "good", 
            "rClarity": 5, 
            "rClass": "MCB150", 
            "rComments": "Brad is a truly exceptional professor. I can't imagine having a better experience in MCB 150. Brad truly cares about his students and makes himself available regularly for the student's convenience. It isn't hard to tell that Brad has a knack for teaching. He makes what seems like an impossible course enjoyable. Would definitely recommend his class", 
            "rDate": "12/05/2014", 
            "rEasy": 4, 
            "rEasyString": "4.0", 
            "rErrorMsg": null, 
            "rHelpful": 5, 
            "rInterest": "Really into it", 
            "rOverall": 5, 
            "rOverallString": "5.0", 
            "rStatus": 1, 
            "rTextBookUse": "Yes", 
            "rWouldTakeAgain": "N/A", 
            "sId": 1112, 
            "takenForCredit": "Yes", 
            "teacher": null, 
            "teacherGrade": "N/A", 
            "teacherRatingTags": [
                "Amazing lectures", 
                "Tough Grader", 
                "Respected by students"
            ], 
            "unUsefulGrouping": "people", 
            "usefulGrouping": "people"
        }, 
        {
            "attendance": "Mandatory", 
            "clarityColor": "good", 
            "easyColor": "average", 
            "helpColor": "good", 
            "helpCount": 0, 
            "id": 23909791, 
            "notHelpCount": 4, 
            "onlineClass": "", 
            "quality": "good", 
            "rClarity": 5, 
            "rClass": "MCB150", 
            "rComments": "The BEST teacher ever had. Took a bio course a year ago and HATED it. Everything was like a confusing web of terms and I hated it all. at first I dreaded taking mcb 150.  2 weeks later, I loved bio, loved going to class. Brad made everything make so much sense. He provided us with all info needed for exams. no joke here, got 100 on the third exam", 
            "rDate": "11/30/2014", 
            "rEasy": 3, 
            "rEasyString": "3.0", 
            "rErrorMsg": null, 
            "rHelpful": 4, 
            "rInterest": "It's my life", 
            "rOverall": 4.5, 
            "rOverallString": "4.5", 
            "rStatus": 1, 
            "rTextBookUse": "No", 
            "rWouldTakeAgain": "Yes", 
            "sId": 1112, 
            "takenForCredit": "Yes", 
            "teacher": null, 
            "teacherGrade": "A+", 
            "teacherRatingTags": [
                "Clear grading criteria", 
                "Amazing lectures"
            ], 
            "unUsefulGrouping": "people", 
            "usefulGrouping": "people"
        }, 
        {
            "attendance": "N/A", 
            "clarityColor": "good", 
            "easyColor": "good", 
            "helpColor": "good", 
            "helpCount": 0, 
            "id": 23800708, 
            "notHelpCount": 0, 
            "onlineClass": "", 
            "quality": "good", 
            "rClarity": 4, 
            "rClass": "MCB150", 
            "rComments": "Mehrtens explains everything very well and can help with any questions but he makes the exams ridiculously difficult. I wouldn't take the class if you don't have to but if you're really passionate about the subject then it might be worth it. The system for class participation really sucks. Logging in before class starts can sometimes be a challenge", 
            "rDate": "11/12/2014", 
            "rEasy": 4, 
            "rEasyString": "4.0", 
            "rErrorMsg": null, 
            "rHelpful": 5, 
            "rInterest": "Really into it", 
            "rOverall": 4.5, 
            "rOverallString": "4.5", 
            "rStatus": 1, 
            "rTextBookUse": "Yes", 
            "rWouldTakeAgain": "N/A", 
            "sId": 1112, 
            "takenForCredit": "Yes", 
            "teacher": null, 
            "teacherGrade": "B+", 
            "teacherRatingTags": [
                "Tough Grader", 
                "Skip class? You won't pass."
            ], 
            "unUsefulGrouping": "people", 
            "usefulGrouping": "people"
        }, 
        {
            "attendance": "N/A", 
            "clarityColor": "good", 
            "easyColor": "average", 
            "helpColor": "good", 
            "helpCount": 0, 
            "id": 23522558, 
            "notHelpCount": 0, 
            "onlineClass": "online", 
            "quality": "good", 
            "rClarity": 5, 
            "rClass": "MCB150", 
            "rComments": "Brad is the bomb. You do have to work hard in this class to get the grade you want, but Brad helps your every step of the way. He provides you with all of the materials you need and is very clear about the content. I learned an incredible amount of material and feel very prepared for any other MCB class I have to take in the future.", 
            "rDate": "08/12/2014", 
            "rEasy": 3, 
            "rEasyString": "3.0", 
            "rErrorMsg": null, 
            "rHelpful": 5, 
            "rInterest": "It's my life", 
            "rOverall": 5, 
            "rOverallString": "5.0", 
            "rStatus": 1, 
            "rTextBookUse": "No", 
            "rWouldTakeAgain": "N/A", 
            "sId": 1112, 
            "takenForCredit": "Yes", 
            "teacher": null, 
            "teacherGrade": "N/A", 
            "teacherRatingTags": [], 
            "unUsefulGrouping": "people", 
            "usefulGrouping": "people"
        }, 
        {
            "attendance": "Mandatory", 
            "clarityColor": "good", 
            "easyColor": "good", 
            "helpColor": "good", 
            "helpCount": 0, 
            "id": 23205859, 
            "notHelpCount": 1, 
            "onlineClass": "online", 
            "quality": "good", 
            "rClarity": 5, 
            "rClass": "MCB150", 
            "rComments": "I took Online over summer failed (SUPER HARD). Then in the fall in class got a B+. HAVE TO attend lecture to pass exams. About 2 questions per exam come from the book. Most questions are what he SAYS in lecture. You have to work for this grade. Studying the night before WILL NOT WORK. Only take if it is a requirement to graduate.", 
            "rDate": "05/09/2014", 
            "rEasy": 4, 
            "rEasyString": "4.0", 
            "rErrorMsg": null, 
            "rHelpful": 5, 
            "rInterest": "Sorta interested", 
            "rOverall": 5, 
            "rOverallString": "5.0", 
            "rStatus": 1, 
            "rTextBookUse": "No", 
            "rWouldTakeAgain": "N/A", 
            "sId": 1112, 
            "takenForCredit": "Yes", 
            "teacher": null, 
            "teacherGrade": "B+", 
            "teacherRatingTags": [], 
            "unUsefulGrouping": "person", 
            "usefulGrouping": "people"
        }, 
        {
            "attendance": "Mandatory", 
            "clarityColor": "good", 
            "easyColor": "poor", 
            "helpColor": "good", 
            "helpCount": 2, 
            "id": 23146359, 
            "notHelpCount": 0, 
            "onlineClass": "", 
            "quality": "good", 
            "rClarity": 5, 
            "rClass": "MCB150", 
            "rComments": "I Love this guys teaching! BEST TEACHER YET! You really have to understand concepts and biological methods for exams but he really prepares you for them. Relisten to lectures (recordings) and screencasts. Ive never had such a good professor. He reexplains concepts in different aspects and repeats them several times. really prepares you for mcb 250", 
            "rDate": "05/01/2014", 
            "rEasy": 1, 
            "rEasyString": "1.0", 
            "rErrorMsg": null, 
            "rHelpful": 5, 
            "rInterest": "It's my life", 
            "rOverall": 5, 
            "rOverallString": "5.0", 
            "rStatus": 1, 
            "rTextBookUse": "No", 
            "rWouldTakeAgain": "N/A", 
            "sId": 1112, 
            "takenForCredit": "N/A", 
            "teacher": null, 
            "teacherGrade": "A", 
            "teacherRatingTags": [], 
            "unUsefulGrouping": "people", 
            "usefulGrouping": "people"
        }, 
        {
            "attendance": "N/A", 
            "clarityColor": "good", 
            "easyColor": "average", 
            "helpColor": "good", 
            "helpCount": 1, 
            "id": 23089697, 
            "notHelpCount": 0, 
            "onlineClass": "", 
            "quality": "good", 
            "rClarity": 5, 
            "rClass": "MCB150", 
            "rComments": "Amazing teacher. knows how to explain concepts well. exams are 99% lecture, 1% txtbk. for exams: recrd lectrs, study slides, watch screencasts, skim txtbk. got As on exams. funny, makes class interesting. never even tempted to fall asleep in class. hahah see what he does if  your phone goes off. but seriously best teacher yet. an A is def possible", 
            "rDate": "04/24/2014", 
            "rEasy": 2, 
            "rEasyString": "2.0", 
            "rErrorMsg": null, 
            "rHelpful": 4, 
            "rInterest": "It's my life", 
            "rOverall": 4.5, 
            "rOverallString": "4.5", 
            "rStatus": 1, 
            "rTextBookUse": "Yes", 
            "rWouldTakeAgain": "N/A", 
            "sId": 1112, 
            "takenForCredit": "N/A", 
            "teacher": null, 
            "teacherGrade": "N/A", 
            "teacherRatingTags": [], 
            "unUsefulGrouping": "people", 
            "usefulGrouping": "person"
        }, 
        {
            "attendance": "N/A", 
            "clarityColor": "good", 
            "easyColor": "good", 
            "helpColor": "good", 
            "helpCount": 1, 
            "id": 23022251, 
            "notHelpCount": 0, 
            "onlineClass": "", 
            "quality": "good", 
            "rClarity": 5, 
            "rClass": "MCB150", 
            "rComments": "The class is though because there is so much detail but Brad makes sure you have the necessary materials to do well in this class. You learn so much from this class, its by far my favorite class at UIUC so far. If you put time into it, you can definitely get an A. Brad is great at explaining things and he wants everyone to do well in his class.", 
            "rDate": "04/10/2014", 
            "rEasy": 5, 
            "rEasyString": "5.0", 
            "rErrorMsg": null, 
            "rHelpful": 5, 
            "rInterest": "It's my life", 
            "rOverall": 5, 
            "rOverallString": "5.0", 
            "rStatus": 1, 
            "rTextBookUse": "Yes", 
            "rWouldTakeAgain": "N/A", 
            "sId": 1112, 
            "takenForCredit": "N/A", 
            "teacher": null, 
            "teacherGrade": "N/A", 
            "teacherRatingTags": [], 
            "unUsefulGrouping": "people", 
            "usefulGrouping": "person"
        }, 
        {
            "attendance": "N/A", 
            "clarityColor": "poor", 
            "easyColor": "good", 
            "helpColor": "poor", 
            "helpCount": 0, 
            "id": 22984056, 
            "notHelpCount": 7, 
            "onlineClass": "", 
            "quality": "poor", 
            "rClarity": 1, 
            "rClass": "MCB140", 
            "rComments": "I HATED this class and this professor. His lectures were awful and he only emphasized the unimportant material on the test. He is also very condescending to students when they approach him to ask questions. If it can be avoided, do not take this class.", 
            "rDate": "04/03/2014", 
            "rEasy": 5, 
            "rEasyString": "5.0", 
            "rErrorMsg": null, 
            "rHelpful": 1, 
            "rInterest": "Meh", 
            "rOverall": 1, 
            "rOverallString": "1.0", 
            "rStatus": 3, 
            "rTextBookUse": "Yes", 
            "rWouldTakeAgain": "N/A", 
            "sId": 1112, 
            "takenForCredit": "N/A", 
            "teacher": null, 
            "teacherGrade": "N/A", 
            "teacherRatingTags": [], 
            "unUsefulGrouping": "people", 
            "usefulGrouping": "people"
        }, 
        {
            "attendance": "N/A", 
            "clarityColor": "poor", 
            "easyColor": "good", 
            "helpColor": "poor", 
            "helpCount": 0, 
            "id": 22915902, 
            "notHelpCount": 4, 
            "onlineClass": "", 
            "quality": "poor", 
            "rClarity": 1, 
            "rClass": "MCB150", 
            "rComments": "I don't know what people are saying about lectures they are useless he just says the same damn thing four times with no detail what so ever. Then the test are about minute details he said you don't have to know or are on the next subject in class. oh and the book ins't detailed either.", 
            "rDate": "03/16/2014", 
            "rEasy": 5, 
            "rEasyString": "5.0", 
            "rErrorMsg": null, 
            "rHelpful": 2, 
            "rInterest": "Really into it", 
            "rOverall": 1.5, 
            "rOverallString": "1.5", 
            "rStatus": 1, 
            "rTextBookUse": "Yes", 
            "rWouldTakeAgain": "N/A", 
            "sId": 1112, 
            "takenForCredit": "N/A", 
            "teacher": null, 
            "teacherGrade": "N/A", 
            "teacherRatingTags": [], 
            "unUsefulGrouping": "people", 
            "usefulGrouping": "people"
        }, 
        {
            "attendance": "N/A", 
            "clarityColor": "good", 
            "easyColor": "good", 
            "helpColor": "good", 
            "helpCount": 1, 
            "id": 22775732, 
            "notHelpCount": 0, 
            "onlineClass": "", 
            "quality": "good", 
            "rClarity": 5, 
            "rClass": "MCB150", 
            "rComments": "One of the hardest classes I've taken in two years here - the amount of content you go through is ridiculous for a semester long course. That said, Brad is very good at explaining concepts and helping you out if you need it, but can seem condescending at times during lecture. Take the exams very seriously from the start and you'll be fine", 
            "rDate": "01/21/2014", 
            "rEasy": 5, 
            "rEasyString": "5.0", 
            "rErrorMsg": null, 
            "rHelpful": 5, 
            "rInterest": "Sorta interested", 
            "rOverall": 5, 
            "rOverallString": "5.0", 
            "rStatus": 1, 
            "rTextBookUse": "Yes", 
            "rWouldTakeAgain": "N/A", 
            "sId": 1112, 
            "takenForCredit": "N/A", 
            "teacher": null, 
            "teacherGrade": "N/A", 
            "teacherRatingTags": [], 
            "unUsefulGrouping": "people", 
            "usefulGrouping": "person"
        }, 
        {
            "attendance": "N/A", 
            "clarityColor": "good", 
            "easyColor": "good", 
            "helpColor": "good", 
            "helpCount": 0, 
            "id": 22611483, 
            "notHelpCount": 0, 
            "onlineClass": "", 
            "quality": "good", 
            "rClarity": 5, 
            "rClass": "MCB150", 
            "rComments": "Class is tough, but if you go to class and RECORD lectures you should do fine. Its pretty easy to get an A- (you can get 70% on exams and get 100% on hw and you will get the A-), to get an A (you can get 80% on exams and get 100% on hw). Overall he is my best professor freshman year.", 
            "rDate": "12/19/2013", 
            "rEasy": 4, 
            "rEasyString": "4.0", 
            "rErrorMsg": null, 
            "rHelpful": 5, 
            "rInterest": "Really into it", 
            "rOverall": 5, 
            "rOverallString": "5.0", 
            "rStatus": 1, 
            "rTextBookUse": "No", 
            "rWouldTakeAgain": "N/A", 
            "sId": 1112, 
            "takenForCredit": "N/A", 
            "teacher": null, 
            "teacherGrade": "N/A", 
            "teacherRatingTags": [], 
            "unUsefulGrouping": "people", 
            "usefulGrouping": "people"
        }, 
        {
            "attendance": "N/A", 
            "clarityColor": "good", 
            "easyColor": "good", 
            "helpColor": "good", 
            "helpCount": 0, 
            "id": 22576046, 
            "notHelpCount": 0, 
            "onlineClass": "", 
            "quality": "good", 
            "rClarity": 5, 
            "rClass": "MCB150", 
            "rComments": "Brad Mehrtens is a great professor, don't get me wrong, but his lectures are VERY ANNOYING. His voice can be very condescending when he means to be thorough, like he's speaking to fifth graders. He also seems extremely rehearsed, partly since he's taught the course for about 20 semesters.... Other than that, his content is all clear and concise.", 
            "rDate": "12/16/2013", 
            "rEasy": 5, 
            "rEasyString": "5.0", 
            "rErrorMsg": null, 
            "rHelpful": 4, 
            "rInterest": "Meh", 
            "rOverall": 4.5, 
            "rOverallString": "4.5", 
            "rStatus": 1, 
            "rTextBookUse": "Yes", 
            "rWouldTakeAgain": "N/A", 
            "sId": 1112, 
            "takenForCredit": "N/A", 
            "teacher": null, 
            "teacherGrade": "N/A", 
            "teacherRatingTags": [], 
            "unUsefulGrouping": "people", 
            "usefulGrouping": "people"
        }, 
        {
            "attendance": "N/A", 
            "clarityColor": "good", 
            "easyColor": "average", 
            "helpColor": "good", 
            "helpCount": 1, 
            "id": 22494300, 
            "notHelpCount": 0, 
            "onlineClass": "", 
            "quality": "good", 
            "rClarity": 5, 
            "rClass": "MCB150", 
            "rComments": "Bradley Mehrtens is the man.  He legitimately is interested in molecular and cellular biology and he tells the best jokes. If I could grow up to be one person it would be Brad.", 
            "rDate": "12/10/2013", 
            "rEasy": 2, 
            "rEasyString": "2.0", 
            "rErrorMsg": null, 
            "rHelpful": 5, 
            "rInterest": "Sorta interested", 
            "rOverall": 5, 
            "rOverallString": "5.0", 
            "rStatus": 1, 
            "rTextBookUse": "No", 
            "rWouldTakeAgain": "N/A", 
            "sId": 1112, 
            "takenForCredit": "N/A", 
            "teacher": null, 
            "teacherGrade": "N/A", 
            "teacherRatingTags": [], 
            "unUsefulGrouping": "people", 
            "usefulGrouping": "person"
        }
    ], 
    "remaining": 163
}