{
    "ratings": [
        {
            "attendance": "N/A", 
            "clarityColor": "good", 
            "easyColor": "average", 
            "helpColor": "good", 
            "helpCount": 0, 
            "id": 13035550, 
            "notHelpCount": 0, 
            "onlineClass": "", 
            "quality": "good", 
            "rClarity": 5, 
            "rClass": "ARTF105", 
            "rComments": "This guy is great. He's extremely happy, nice, and helpful. His class is pretty fun and he just rocks. Just make sure you get to class on time!", 
            "rDate": "04/19/2007", 
            "rEasy": 2, 
            "rEasyString": "2.0", 
            "rErrorMsg": null, 
            "rHelpful": 5, 
            "rInterest": "It's my life", 
            "rOverall": 5, 
            "rOverallString": "5.0", 
            "rStatus": 1, 
            "rTextBookUse": "No", 
            "rWouldTakeAgain": "N/A", 
            "sId": 1112, 
            "takenForCredit": "N/A", 
            "teacher": null, 
            "teacherGrade": "N/A", 
            "teacherRatingTags": [], 
            "unUsefulGrouping": "people", 
            "usefulGrouping": "people"
        }, 
        {
            "attendance": "N/A", 
            "clarityColor": "good", 
            "easyColor": "average", 
            "helpColor": "good", 
            "helpCount": 0, 
            "id": 10194005, 
            "notHelpCount": 0, 
            "onlineClass": "", 
            "quality": "good", 
            "rClarity": 5, 
            "rClass": "DESIGNII", 
            "rComments": "Very pleasant and cares about his students. I was a **** up at design because it wasn't my main desire, but he helped me integrate my art into design. Not bad.", 
            "rDate": "09/01/2005", 
            "rEasy": 2, 
            "rEasyString": "2.0", 
            "rErrorMsg": null, 
            "rHelpful": 5, 
            "rInterest": "Sorta interested", 
            "rOverall": 5, 
            "rOverallString": "5.0", 
            "rStatus": 1, 
            "rTextBookUse": "N/A", 
            "rWouldTakeAgain": "N/A", 
            "sId": 1112, 
            "takenForCredit": "N/A", 
            "teacher": null, 
            "teacherGrade": "N/A", 
            "teacherRatingTags": [], 
            "unUsefulGrouping": "people", 
            "usefulGrouping": "people"
        }, 
        {
            "attendance": "N/A", 
            "clarityColor": "good", 
            "easyColor": "average", 
            "helpColor": "good", 
            "helpCount": 0, 
            "id": 1298477, 
            "notHelpCount": 0, 
            "onlineClass": "", 
            "quality": "good", 
            "rClarity": 4, 
            "rClass": "ARTD", 
            "rComments": "what a happy man", 
            "rDate": "11/11/2003", 
            "rEasy": 3, 
            "rEasyString": "3.0", 
            "rErrorMsg": null, 
            "rHelpful": 4, 
            "rInterest": "N/A", 
            "rOverall": 4, 
            "rOverallString": "4.0", 
            "rStatus": 1, 
            "rTextBookUse": "N/A", 
            "rWouldTakeAgain": "N/A", 
            "sId": 1112, 
            "takenForCredit": "N/A", 
            "teacher": null, 
            "teacherGrade": "N/A", 
            "teacherRatingTags": [], 
            "unUsefulGrouping": "people", 
            "usefulGrouping": "people"
        }, 
        {
            "attendance": "N/A", 
            "clarityColor": "good", 
            "easyColor": "average", 
            "helpColor": "good", 
            "helpCount": 0, 
            "id": 936463, 
            "notHelpCount": 0, 
            "onlineClass": "", 
            "quality": "good", 
            "rClarity": 5, 
            "rClass": "DES117", 
            "rComments": "No Comments", 
            "rDate": "05/07/2003", 
            "rEasy": 3, 
            "rEasyString": "3.0", 
            "rErrorMsg": null, 
            "rHelpful": 5, 
            "rInterest": "N/A", 
            "rOverall": 5, 
            "rOverallString": "5.0", 
            "rStatus": 1, 
            "rTextBookUse": "N/A", 
            "rWouldTakeAgain": "N/A", 
            "sId": 1112, 
            "takenForCredit": "N/A", 
            "teacher": null, 
            "teacherGrade": "N/A", 
            "teacherRatingTags": [], 
            "unUsefulGrouping": "people", 
            "usefulGrouping": "people"
        }
    ], 
    "remaining": 0
}