{
    "ratings": [
        {
            "attendance": "N/A", 
            "clarityColor": "average", 
            "easyColor": "good", 
            "helpColor": "average", 
            "helpCount": 0, 
            "id": 2418679, 
            "notHelpCount": 0, 
            "onlineClass": "", 
            "quality": "average", 
            "rClarity": 2, 
            "rClass": "CHEM231", 
            "rComments": "Are you people out of your minds&#63; While Moore is a nice person, and I should know because I did participate in his C- agreement Saturday sessions, his exams are way too difficult. One time his assistant professor couldn't do some of the problems.", 
            "rDate": "08/25/2004", 
            "rEasy": 5, 
            "rEasyString": "5.0", 
            "rErrorMsg": null, 
            "rHelpful": 3, 
            "rInterest": "N/A", 
            "rOverall": 2.5, 
            "rOverallString": "2.5", 
            "rStatus": 1, 
            "rTextBookUse": "N/A", 
            "rWouldTakeAgain": "N/A", 
            "sId": 1112, 
            "takenForCredit": "N/A", 
            "teacher": null, 
            "teacherGrade": "N/A", 
            "teacherRatingTags": [], 
            "unUsefulGrouping": "people", 
            "usefulGrouping": "people"
        }, 
        {
            "attendance": "N/A", 
            "clarityColor": "good", 
            "easyColor": "average", 
            "helpColor": "good", 
            "helpCount": 0, 
            "id": 2304212, 
            "notHelpCount": 0, 
            "onlineClass": "", 
            "quality": "good", 
            "rClarity": 5, 
            "rClass": "CHEM223", 
            "rComments": "Excellent professor, knows how to teach organic chemistry.  Stick to it, you still have to work for it.", 
            "rDate": "07/09/2004", 
            "rEasy": 2, 
            "rEasyString": "2.0", 
            "rErrorMsg": null, 
            "rHelpful": 5, 
            "rInterest": "N/A", 
            "rOverall": 5, 
            "rOverallString": "5.0", 
            "rStatus": 1, 
            "rTextBookUse": "N/A", 
            "rWouldTakeAgain": "N/A", 
            "sId": 1112, 
            "takenForCredit": "N/A", 
            "teacher": null, 
            "teacherGrade": "N/A", 
            "teacherRatingTags": [], 
            "unUsefulGrouping": "people", 
            "usefulGrouping": "people"
        }, 
        {
            "attendance": "N/A", 
            "clarityColor": "good", 
            "easyColor": "good", 
            "helpColor": "good", 
            "helpCount": 0, 
            "id": 1752777, 
            "notHelpCount": 0, 
            "onlineClass": "", 
            "quality": "good", 
            "rClarity": 5, 
            "rClass": "CHEM331", 
            "rComments": "He's easy to talk to and is very helpful.  He definitely shows an interest in the student.", 
            "rDate": "02/25/2004", 
            "rEasy": 4, 
            "rEasyString": "4.0", 
            "rErrorMsg": null, 
            "rHelpful": 5, 
            "rInterest": "N/A", 
            "rOverall": 5, 
            "rOverallString": "5.0", 
            "rStatus": 1, 
            "rTextBookUse": "N/A", 
            "rWouldTakeAgain": "N/A", 
            "sId": 1112, 
            "takenForCredit": "N/A", 
            "teacher": null, 
            "teacherGrade": "N/A", 
            "teacherRatingTags": [], 
            "unUsefulGrouping": "people", 
            "usefulGrouping": "people"
        }
    ], 
    "remaining": 0
}